tentaclio/__init__.py
tentaclio/__main__.py
tentaclio/protocols.py
tentaclio/registry.py
tentaclio/urls.py
tentaclio/clients/__init__.py
tentaclio/clients/base_client.py
tentaclio/clients/decorators.py
tentaclio/clients/exceptions.py
tentaclio/clients/ftp_client.py
tentaclio/clients/http_client.py
tentaclio/clients/importer.py
tentaclio/clients/local_fs_client.py
tentaclio/clients/sqla_client.py
tentaclio/credentials/__init__.py
tentaclio/credentials/api.py
tentaclio/credentials/env.py
tentaclio/credentials/injection.py
tentaclio/credentials/reader.py
tentaclio/databases/__init__.py
tentaclio/databases/api.py
tentaclio/databases/db_registry.py
tentaclio/fs/__init__.py
tentaclio/fs/api.py
tentaclio/fs/copier.py
tentaclio/fs/copiers.py
tentaclio/fs/remover.py
tentaclio/fs/scanner.py
tentaclio/fs/scanners.py
tentaclio/hooks/__init__.py
tentaclio/hooks/slack_hook.py
tentaclio/streams/__init__.py
tentaclio/streams/api.py
tentaclio/streams/base_stream.py
tentaclio/streams/csv_db_stream.py
tentaclio/streams/stream_client_handler.py
tentaclio/streams/stream_registry.py
tentaclio-1.3.7.dist-info/licenses/LICENSE.txt
tentaclio-1.3.7.dist-info/METADATA
tentaclio-1.3.7.dist-info/WHEEL
tentaclio-1.3.7.dist-info/top_level.txt
tentaclio-1.3.7.dist-info/RECORD
