Metadata-Version: 2.4
Name: tentaclio
Version: 1.3.7
Summary: Unification of data connectors for distributed data tasks
Home-page: https://github.com/octoenergy/tentaclio
Author: Octopus Energy
Author-email: nerds@octoenergy.com
License: MIT
Classifier: Development Status :: 5 - Production/Stable
Classifier: Intended Audience :: Developers
Classifier: License :: OSI Approved :: MIT License
Classifier: Operating System :: OS Independent
Classifier: Programming Language :: Python :: 3
Classifier: Programming Language :: Python :: 3.6
Classifier: Programming Language :: Python :: 3.7
Classifier: Programming Language :: Python :: 3.8
Classifier: Programming Language :: Python :: 3.9
Classifier: Typing :: Typed
License-File: LICENSE.txt
Requires-Dist: urllib3>=1.24.2
Requires-Dist: requests
Requires-Dist: sqlalchemy>=1.4
Requires-Dist: paramiko<4.0.0
Requires-Dist: pandas
Requires-Dist: click
Requires-Dist: pyyaml
Requires-Dist: importlib_metadata>3.7.0
Provides-Extra: s3
Requires-Dist: tentaclio_s3; extra == "s3"
Provides-Extra: athena
Requires-Dist: tentaclio_athena; extra == "athena"
Provides-Extra: postgres
Requires-Dist: tentaclio_postgres; extra == "postgres"
Provides-Extra: databricks
Requires-Dist: tentaclio_databricks>=1.0.0; extra == "databricks"
Provides-Extra: gdrive
Requires-Dist: tentaclio_gdrive; extra == "gdrive"
Provides-Extra: gs
Requires-Dist: tentaclio_gs; extra == "gs"
Provides-Extra: snowflake
Requires-Dist: tentaclio_snowflake; extra == "snowflake"
Dynamic: author
Dynamic: author-email
Dynamic: classifier
Dynamic: description
Dynamic: description-content-type
Dynamic: home-page
Dynamic: license
Dynamic: license-file
Dynamic: provides-extra
Dynamic: requires-dist
Dynamic: summary
